mycelial-0.2.1.dist-info/METADATA
mycelial-0.2.1.dist-info/WHEEL
mycelial/_mycelial.py
mycelial/transport/__init__.py
mycelial/transport/relay/v0alpha.py
mycelial/transport/relay/__init__.py
mycelial/__init__.py
mycelial/mycelial.cpython-39-arm-linux-gnueabihf.so
mycelial-0.2.1.dist-info/RECORD
