Metadata-Version: 2.1
Name: mycelial
Version: 0.2.1
Requires-Dist: websockets==10.3
Summary: mycelial python bindings
License: Apache-2.0
Requires-Python: >=3.9
